pyutool/__init__.py
pyutool/game_engine.py
pyutool/recording/__init__.py
pyutool/recording/analysis/__init__.py
pyutool/recording/analysis/reporter.py
pyutool/recording/checks/__init__.py
pyutool/recording/checks/checkexecutor_base.py
pyutool/recording/checks/common.py
pyutool/recording/checks/decorator_checker.py
pyutool/recording/checks/encoding_checker.py
pyutool/recording/checks/factory.py
pyutool/recording/checks/key_checker.py
pyutool/recording/checks/logger_checker.py
pyutool/recording/checks/path_checker.py
pyutool/recording/checks/range_checker.py
pyutool/recording/checks/type_checker.py
pyutool/recording/core/__init__.py
pyutool/recording/core/config.py
pyutool/recording/core/handler.py
pyutool/recording/core/logger.py
pyutool/recording/errors/__init__.py
pyutool/recording/errors/base.py
pyutool/recording/errors/errors.py
pyutool/recording/errors/functions.py
pyutool/recording/errors/parameter.py
pyutool/recording/errors/path.py
pyutool/recording/errors/validation.py
pyutool/recording/utils/__init__.py
pyutool/recording/utils/log_parsing.py
pyutool/recording/utils/object.py
pyutool/recording/utils/path.py
pyutool/recording/utils/stack.py
pyutool/umodules/__init__.py
pyutool/umodules/new_re.py
pyutool/umodules/ufunctools.py
pyutool/umodules/cli/__init__.py
pyutool/umodules/cli/cli_utils.py
pyutool/umodules/cli/render.py
pyutool/umodules/file/__init__.py
pyutool/umodules/file/configer.py
pyutool/umodules/file/edit_file.py
pyutool/umodules/password/encoder.py
pyutool/umodules/password/password_book_editor.py
pyutool/umodules/password/verification_code.py
pyutool/umodules/predefine/__init__.py
pyutool/umodules/predefine/advanced_class.py
pyutool/umodules/predefine/limited_type.py
pyutool/umodules/predefine/rgb_colors.py
pyutool/umodules/predefine/set_default.py
pyutool/utools/__init__.py
pyutool/utools/directory_structure.py
pyutool/utools/file_to_desktop.py
pyutool/utools/import_requirements.py
pyutool/utools/produce_bat.py
pyutool-0.0.3.dist-info/licenses/LICENSE
pyutool-0.0.3.dist-info/METADATA
pyutool-0.0.3.dist-info/WHEEL
pyutool-0.0.3.dist-info/top_level.txt
pyutool-0.0.3.dist-info/RECORD
