Metadata-Version: 2.4
Name: pyutool
Version: 0.0.3
Summary: The log module is currently implemented to replace logging. And other small wheels
Home-page: https://github.com/YLtop01/my-awesome-project
Author: YL_top01
Author-email: YL_top01 <2787284002@qq.com>
Requires-Python: >=3.6
License-File: LICENSE
Dynamic: author
Dynamic: home-page
Dynamic: license-file
Dynamic: requires-python
